<?xml version = '1.0' encoding='UTF-8'?>
<DetalheParlamentar xmlns:xsi="http://www.w3.org/2001/XMLSchema-instance" xsi:noNamespaceSchemaLocation="http://legis.senado.leg.br/dadosabertos/dados/DetalheParlamentarv5.xsd">
   <Metadados>
      <Versao>06/11/2020 20:16:45</Versao><VersaoServico>5</VersaoServico><DataVersaoServico>2017-02-01</DataVersaoServico><DescricaoDataSet>Informações atuais sobre o parlamentar
      
      Evoluções:
      06/09/2019
      - criada nova Tag &quot;Telefones&quot;
      - os telefones deixam de ser exibidos na tag &quot;TelefoneParlamentar&quot; e passam a vir na tag &quot;Telefones&quot;, especificamente em &quot;NumeroTelefone&quot;. 
      - O fax deixa de ser exibido na tag &quot;FaxParlamentar&quot; e passa a ser informado dentro de &quot;Telefones&quot; com o valor &quot;Sim&quot; para a tag &quot;indicadorFax&quot;.
      28/01/2020
      - criada nova Tag &quot;HistoricoAcademico&quot;, com os cursos do parlamentar.
      - criada nova Tag &quot;Profissoes&quot;, com as profissões do parlamentar.</DescricaoDataSet>
   </Metadados>
   <Parlamentar>
      <IdentificacaoParlamentar><CodigoParlamentar>5988</CodigoParlamentar><CodigoPublicoNaLegAtual>854</CodigoPublicoNaLegAtual><NomeParlamentar>Soraya Thronicke</NomeParlamentar><NomeCompletoParlamentar>Soraya Vieira Thronicke</NomeCompletoParlamentar><SexoParlamentar>Feminino</SexoParlamentar><FormaTratamento>Senadora </FormaTratamento><UrlFotoParlamentar>http://www.senado.leg.br/senadores/img/fotos-oficiais/senador5988.jpg</UrlFotoParlamentar><UrlPaginaParlamentar>http://www25.senado.leg.br/web/senadores/senador/-/perfil/5988</UrlPaginaParlamentar><EmailParlamentar>sen.sorayathronicke@senado.leg.br</EmailParlamentar><SiglaPartidoParlamentar>PSL</SiglaPartidoParlamentar><UfParlamentar>MS</UfParlamentar></IdentificacaoParlamentar><DadosBasicosParlamentar><DataNascimento>1973-06-01</DataNascimento><Naturalidade>Dourados</Naturalidade><UfNaturalidade>MS</UfNaturalidade><EnderecoParlamentar>Senado Federal Edifício Principal   Ala Dinarte Mariz Gabinete 01</EnderecoParlamentar></DadosBasicosParlamentar><Telefones><Telefone><NumeroTelefone>33031775</NumeroTelefone><OrdemPublicacao>1</OrdemPublicacao><IndicadorFax>Não</IndicadorFax></Telefone></Telefones><MandatoAtual><CodigoMandato>561</CodigoMandato><UfParlamentar>MS</UfParlamentar><PrimeiraLegislaturaDoMandato><NumeroLegislatura>56</NumeroLegislatura><DataInicio>2019-02-01</DataInicio><DataFim>2023-01-31</DataFim></PrimeiraLegislaturaDoMandato><SegundaLegislaturaDoMandato><NumeroLegislatura>57</NumeroLegislatura><DataInicio>2023-02-01</DataInicio><DataFim>2027-01-31</DataFim></SegundaLegislaturaDoMandato><DescricaoParticipacao>Titular</DescricaoParticipacao><Suplentes><Suplente><DescricaoParticipacao>1º Suplente</DescricaoParticipacao><CodigoParlamentar>5986</CodigoParlamentar><NomeParlamentar>Rodolfo Nogueira</NomeParlamentar></Suplente><Suplente><DescricaoParticipacao>2º Suplente</DescricaoParticipacao><CodigoParlamentar>5987</CodigoParlamentar><NomeParlamentar>Danny Fabricio</NomeParlamentar></Suplente></Suplentes><Exercicios><Exercicio><CodigoExercicio>2937</CodigoExercicio><DataInicio>2019-02-01</DataInicio></Exercicio></Exercicios></MandatoAtual><FiliacaoAtual><Partido><CodigoPartido>85</CodigoPartido><SiglaPartido>PSL</SiglaPartido><NomePartido>Partido Social Liberal</NomePartido></Partido><DataFiliacao>2019-01-01</DataFiliacao></FiliacaoAtual><MembroAtualComissoes><Comissao><IdentificacaoComissao><CodigoComissao>2386</CodigoComissao><SiglaComissao>CTEPANTANAL</SiglaComissao><NomeComissao>Comissão Temporária Externa para acompanhar as ações de enfrentamento aos incêndios detectados no bioma Pantanal</NomeComissao><SiglaCasaComissao>SF</SiglaCasaComissao><NomeCasaComissao>Senado Federal</NomeCasaComissao></IdentificacaoComissao><DescricaoParticipacao>Titular</DescricaoParticipacao><DataInicio>2020-09-15</DataInicio></Comissao><Comissao><IdentificacaoComissao><CodigoComissao>2115</CodigoComissao><SiglaComissao>GPCOREIADOSUL</SiglaComissao><NomeComissao>Grupo Parlamentar Brasil - Coreia do Sul</NomeComissao><SiglaCasaComissao>CN</SiglaCasaComissao><NomeCasaComissao>Congresso Nacional</NomeCasaComissao></IdentificacaoComissao><DescricaoParticipacao>Titular</DescricaoParticipacao><DataInicio>2020-03-02</DataInicio></Comissao><Comissao><IdentificacaoComissao><CodigoComissao>34</CodigoComissao><SiglaComissao>CCJ</SiglaComissao><NomeComissao>Comissão de Constituição, Justiça e Cidadania</NomeComissao><SiglaCasaComissao>SF</SiglaCasaComissao><NomeCasaComissao>Senado Federal</NomeCasaComissao></IdentificacaoComissao><DescricaoParticipacao>Suplente</DescricaoParticipacao><DataInicio>2019-11-20</DataInicio></Comissao><Comissao><IdentificacaoComissao><CodigoComissao>2266</CodigoComissao><SiglaComissao>FPTGP</SiglaComissao><NomeComissao>Frente Parlamentar para a Transparência dos Gastos Públicos</NomeComissao><SiglaCasaComissao>CN</SiglaCasaComissao><NomeCasaComissao>Congresso Nacional</NomeCasaComissao></IdentificacaoComissao><DescricaoParticipacao>Titular</DescricaoParticipacao><DataInicio>2019-10-22</DataInicio></Comissao><Comissao><IdentificacaoComissao><CodigoComissao>1540</CodigoComissao><SiglaComissao>CDHC</SiglaComissao><NomeComissao>Conselho da Comenda de Direitos Humanos Dom Hélder Câmara</NomeComissao><SiglaCasaComissao>SF</SiglaCasaComissao><NomeCasaComissao>Senado Federal</NomeCasaComissao></IdentificacaoComissao><DescricaoParticipacao>Titular</DescricaoParticipacao><DataInicio>2019-10-15</DataInicio></Comissao><Comissao><IdentificacaoComissao><CodigoComissao>1722</CodigoComissao><SiglaComissao>COI</SiglaComissao><NomeComissao>III - Comitê de Avaliação das Inform. sobre Obras e Serviços com Indícios de Irregularidades Graves</NomeComissao><SiglaCasaComissao>CN</SiglaCasaComissao><NomeCasaComissao>Congresso Nacional</NomeCasaComissao></IdentificacaoComissao><DescricaoParticipacao>Titular</DescricaoParticipacao><DataInicio>2019-10-03</DataInicio></Comissao><Comissao><IdentificacaoComissao><CodigoComissao>834</CodigoComissao><SiglaComissao>CDH</SiglaComissao><NomeComissao>Comissão de Direitos Humanos e Legislação Participativa</NomeComissao><SiglaCasaComissao>SF</SiglaCasaComissao><NomeCasaComissao>Senado Federal</NomeCasaComissao></IdentificacaoComissao><DescricaoParticipacao>Titular</DescricaoParticipacao><DataInicio>2019-10-01</DataInicio></Comissao><Comissao><IdentificacaoComissao><CodigoComissao>2292</CodigoComissao><SiglaComissao>CPMI - Fake News</SiglaComissao><NomeComissao>Comissão Parlamentar Mista de Inquérito - Fake News</NomeComissao><SiglaCasaComissao>CN</SiglaCasaComissao><NomeCasaComissao>Congresso Nacional</NomeCasaComissao></IdentificacaoComissao><DescricaoParticipacao>Titular</DescricaoParticipacao><DataInicio>2019-10-01</DataInicio></Comissao><Comissao><IdentificacaoComissao><CodigoComissao>40</CodigoComissao><SiglaComissao>CAS</SiglaComissao><NomeComissao>Comissão de Assuntos Sociais</NomeComissao><SiglaCasaComissao>SF</SiglaCasaComissao><NomeCasaComissao>Senado Federal</NomeCasaComissao></IdentificacaoComissao><DescricaoParticipacao>Titular</DescricaoParticipacao><DataInicio>2019-10-01</DataInicio></Comissao><Comissao><IdentificacaoComissao><CodigoComissao>2270</CodigoComissao><SiglaComissao>FPJOVEM</SiglaComissao><NomeComissao>Frente Parlamentar em Defesa das Políticas Públicas de Juventude</NomeComissao><SiglaCasaComissao>CN</SiglaCasaComissao><NomeCasaComissao>Congresso Nacional</NomeCasaComissao></IdentificacaoComissao><DescricaoParticipacao>Titular</DescricaoParticipacao><DataInicio>2019-09-11</DataInicio></Comissao><Comissao><IdentificacaoComissao><CodigoComissao>2294</CodigoComissao><SiglaComissao>CTRCC</SiglaComissao><NomeComissao>Comissão Temporária para Reforma do Código Comercial (Art. 374-RISF) - 2019</NomeComissao><SiglaCasaComissao>SF</SiglaCasaComissao><NomeCasaComissao>Senado Federal</NomeCasaComissao></IdentificacaoComissao><DescricaoParticipacao>Titular</DescricaoParticipacao><DataInicio>2019-09-03</DataInicio></Comissao><Comissao><IdentificacaoComissao><CodigoComissao>2293</CodigoComissao><SiglaComissao>CRESTL</SiglaComissao><NomeComissao>Subcomissão Temporária sobre o favorecimento à Leros</NomeComissao><SiglaCasaComissao>SF</SiglaCasaComissao><NomeCasaComissao>Senado Federal</NomeCasaComissao></IdentificacaoComissao><DescricaoParticipacao>Suplente</DescricaoParticipacao><DataInicio>2019-08-30</DataInicio></Comissao><Comissao><IdentificacaoComissao><CodigoComissao>54</CodigoComissao><SiglaComissao>CRE</SiglaComissao><NomeComissao>Comissão de Relações Exteriores e Defesa Nacional</NomeComissao><SiglaCasaComissao>SF</SiglaCasaComissao><NomeCasaComissao>Senado Federal</NomeCasaComissao></IdentificacaoComissao><DescricaoParticipacao>Suplente</DescricaoParticipacao><DataInicio>2019-07-12</DataInicio></Comissao><Comissao><IdentificacaoComissao><CodigoComissao>2279</CodigoComissao><SiglaComissao>CASPCD</SiglaComissao><NomeComissao>Subcomissão Permanente da Pessoa com Deficiência</NomeComissao><SiglaCasaComissao>SF</SiglaCasaComissao><NomeCasaComissao>Senado Federal</NomeCasaComissao></IdentificacaoComissao><DescricaoParticipacao>Suplente</DescricaoParticipacao><DataInicio>2019-05-16</DataInicio></Comissao><Comissao><IdentificacaoComissao><CodigoComissao>2280</CodigoComissao><SiglaComissao>CASDRAR</SiglaComissao><NomeComissao>Subcomissão Temporária sobre Doenças Raras</NomeComissao><SiglaCasaComissao>SF</SiglaCasaComissao><NomeCasaComissao>Senado Federal</NomeCasaComissao></IdentificacaoComissao><DescricaoParticipacao>Suplente</DescricaoParticipacao><DataInicio>2019-05-16</DataInicio></Comissao><Comissao><IdentificacaoComissao><CodigoComissao>2274</CodigoComissao><SiglaComissao>CDHSPB</SiglaComissao><NomeComissao>Subcomissão Temporária sobre o Sistema Penitenciário Brasileiro</NomeComissao><SiglaCasaComissao>SF</SiglaCasaComissao><NomeCasaComissao>Senado Federal</NomeCasaComissao></IdentificacaoComissao><DescricaoParticipacao>Titular</DescricaoParticipacao><DataInicio>2019-05-14</DataInicio></Comissao><Comissao><IdentificacaoComissao><CodigoComissao>1916</CodigoComissao><SiglaComissao>CPCMS</SiglaComissao><NomeComissao>Representação Brasileira no Parlamento do Mercosul</NomeComissao><SiglaCasaComissao>CN</SiglaCasaComissao><NomeCasaComissao>Congresso Nacional</NomeCasaComissao></IdentificacaoComissao><DescricaoParticipacao>Titular</DescricaoParticipacao><DataInicio>2019-04-10</DataInicio></Comissao><Comissao><IdentificacaoComissao><CodigoComissao>2044</CodigoComissao><SiglaComissao>GPCHINA</SiglaComissao><NomeComissao>Grupo Parlamentar Brasil - China</NomeComissao><SiglaCasaComissao>CN</SiglaCasaComissao><NomeCasaComissao>Congresso Nacional</NomeCasaComissao></IdentificacaoComissao><DescricaoParticipacao>Titular</DescricaoParticipacao><DataInicio>2019-03-27</DataInicio></Comissao><Comissao><IdentificacaoComissao><CodigoComissao>2251</CodigoComissao><SiglaComissao>CRESTV</SiglaComissao><NomeComissao>Subcomissão Temporária sobre a Venezuela</NomeComissao><SiglaCasaComissao>SF</SiglaCasaComissao><NomeCasaComissao>Senado Federal</NomeCasaComissao></IdentificacaoComissao><DescricaoParticipacao>Suplente</DescricaoParticipacao><DataInicio>2019-03-14</DataInicio></Comissao><Comissao><IdentificacaoComissao><CodigoComissao>47</CodigoComissao><SiglaComissao>CE</SiglaComissao><NomeComissao>Comissão de Educação, Cultura e Esporte</NomeComissao><SiglaCasaComissao>SF</SiglaCasaComissao><NomeCasaComissao>Senado Federal</NomeCasaComissao></IdentificacaoComissao><DescricaoParticipacao>Suplente</DescricaoParticipacao><DataInicio>2019-02-19</DataInicio></Comissao><Comissao><IdentificacaoComissao><CodigoComissao>50</CodigoComissao><SiglaComissao>CMA</SiglaComissao><NomeComissao>Comissão de Meio Ambiente</NomeComissao><SiglaCasaComissao>SF</SiglaCasaComissao><NomeCasaComissao>Senado Federal</NomeCasaComissao></IdentificacaoComissao><DescricaoParticipacao>Titular</DescricaoParticipacao><DataInicio>2019-02-13</DataInicio></Comissao><Comissao><IdentificacaoComissao><CodigoComissao>1306</CodigoComissao><SiglaComissao>CDR</SiglaComissao><NomeComissao>Comissão de Desenvolvimento Regional e Turismo</NomeComissao><SiglaCasaComissao>SF</SiglaCasaComissao><NomeCasaComissao>Senado Federal</NomeCasaComissao></IdentificacaoComissao><DescricaoParticipacao>Titular</DescricaoParticipacao><DataInicio>2019-02-13</DataInicio></Comissao><Comissao><IdentificacaoComissao><CodigoComissao>1307</CodigoComissao><SiglaComissao>CRA</SiglaComissao><NomeComissao>Comissão de Agricultura e Reforma Agrária</NomeComissao><SiglaCasaComissao>SF</SiglaCasaComissao><NomeCasaComissao>Senado Federal</NomeCasaComissao></IdentificacaoComissao><DescricaoParticipacao>Titular</DescricaoParticipacao><DataInicio>2019-02-13</DataInicio></Comissao></MembroAtualComissoes><CargosAtuais><CargoAtual><IdentificacaoComissao><CodigoComissao>2266</CodigoComissao><SiglaComissao>FPTGP</SiglaComissao><NomeComissao>Frente Parlamentar para a Transparência dos Gastos Públicos</NomeComissao><SiglaCasaComissao>CN</SiglaCasaComissao><NomeCasaComissao>Congresso Nacional</NomeCasaComissao></IdentificacaoComissao><CodigoCargo>1</CodigoCargo><DescricaoCargo>PRESIDENTE</DescricaoCargo><DataInicio>2019-10-23</DataInicio></CargoAtual><CargoAtual><IdentificacaoComissao><CodigoComissao>2294</CodigoComissao><SiglaComissao>CTRCC</SiglaComissao><NomeComissao>Comissão Temporária para Reforma do Código Comercial (Art. 374-RISF) - 2019</NomeComissao><SiglaCasaComissao>SF</SiglaCasaComissao><NomeCasaComissao>Senado Federal</NomeCasaComissao></IdentificacaoComissao><CodigoCargo>152</CodigoCargo><DescricaoCargo>RELATORA</DescricaoCargo><DataInicio>2019-09-04</DataInicio></CargoAtual><CargoAtual><IdentificacaoComissao><CodigoComissao>1307</CodigoComissao><SiglaComissao>CRA</SiglaComissao><NomeComissao>Comissão de Agricultura e Reforma Agrária</NomeComissao><SiglaCasaComissao>SF</SiglaCasaComissao><NomeCasaComissao>Senado Federal</NomeCasaComissao></IdentificacaoComissao><CodigoCargo>1</CodigoCargo><DescricaoCargo>PRESIDENTE</DescricaoCargo><DataInicio>2019-02-14</DataInicio></CargoAtual></CargosAtuais><LiderancasAtuais><Lideranca><Partido><CodigoPartido>85</CodigoPartido><SiglaPartido>PSL</SiglaPartido><NomePartido>Partido Social Liberal</NomePartido></Partido><SiglaCasaLideranca>SF</SiglaCasaLideranca><NomeCasaLideranca>Senado Federal</NomeCasaLideranca><DescricaoTipoLideranca>Vice-líder</DescricaoTipoLideranca><DataDesignacao>2019-10-01</DataDesignacao></Lideranca></LiderancasAtuais><MateriasDeAutoriaTramitando><Materia><IdentificacaoMateria><CodigoMateria>135812</CodigoMateria><SiglaCasaIdentificacaoMateria>SF</SiglaCasaIdentificacaoMateria><NomeCasaIdentificacaoMateria>Senado Federal</NomeCasaIdentificacaoMateria><SiglaSubtipoMateria>PL</SiglaSubtipoMateria><DescricaoSubtipoMateria>PROJETO DE LEI</DescricaoSubtipoMateria><NumeroMateria>01587</NumeroMateria><AnoMateria>2019</AnoMateria><DescricaoObjetivoProcesso>Iniciadora</DescricaoObjetivoProcesso><DescricaoIdentificacaoMateria>PL 1587/2019</DescricaoIdentificacaoMateria></IdentificacaoMateria><EmentaMateria>Altera a Lei nº 9.099, de 26 de setembro de 1995 (Lei dos Juizados Especiais Cíveis e Criminais), para permitir, em sede executiva, o arresto, a citação por hora certa e por edital e a suspensão da execução.</EmentaMateria></Materia><Materia><IdentificacaoMateria><CodigoMateria>135988</CodigoMateria><SiglaCasaIdentificacaoMateria>SF</SiglaCasaIdentificacaoMateria><NomeCasaIdentificacaoMateria>Senado Federal</NomeCasaIdentificacaoMateria><SiglaSubtipoMateria>REQ</SiglaSubtipoMateria><DescricaoSubtipoMateria>REQUERIMENTO</DescricaoSubtipoMateria><NumeroMateria>00008</NumeroMateria><AnoMateria>2019</AnoMateria><SiglaComissaoRequerimento>CRA</SiglaComissaoRequerimento><DescricaoIdentificacaoMateria>REQ 8/2019 - CRA</DescricaoIdentificacaoMateria></IdentificacaoMateria><EmentaMateria>Nos termos do artigo 90, IX, 96-B e 104-B do Regimento Interno do Senado Federal, a Comissão de Agricultura e Reforma Agrária decide selecionar a seguinte Política Pública do Poder Executivo para avaliação no ano de 2019: Política de Comércio Internacional Agropecuário.
      Relator da avaliação: Senador Luis Carlos Heinze.</EmentaMateria></Materia><Materia><IdentificacaoMateria><CodigoMateria>136250</CodigoMateria><SiglaCasaIdentificacaoMateria>SF</SiglaCasaIdentificacaoMateria><NomeCasaIdentificacaoMateria>Senado Federal</NomeCasaIdentificacaoMateria><SiglaSubtipoMateria>REQ</SiglaSubtipoMateria><DescricaoSubtipoMateria>REQUERIMENTO</DescricaoSubtipoMateria><NumeroMateria>00019</NumeroMateria><AnoMateria>2019</AnoMateria><SiglaComissaoRequerimento>CRE</SiglaComissaoRequerimento><DescricaoIdentificacaoMateria>REQ 19/2019 - CRE</DescricaoIdentificacaoMateria></IdentificacaoMateria><EmentaMateria>Requeiro, nos termos do art. 96-B do Regimento Interno do Senado Federal, que a Comissão de Relações Exteriores e Defesa Nacional avalie a política brasileira de adesão à Organização para a Cooperação e Desenvolvimento Econômico (OCDE), no exercício de 2019.</EmentaMateria></Materia><Materia><IdentificacaoMateria><CodigoMateria>136419</CodigoMateria><SiglaCasaIdentificacaoMateria>SF</SiglaCasaIdentificacaoMateria><NomeCasaIdentificacaoMateria>Senado Federal</NomeCasaIdentificacaoMateria><SiglaSubtipoMateria>PL</SiglaSubtipoMateria><DescricaoSubtipoMateria>PROJETO DE LEI</DescricaoSubtipoMateria><NumeroMateria>02450</NumeroMateria><AnoMateria>2019</AnoMateria><DescricaoObjetivoProcesso>Iniciadora</DescricaoObjetivoProcesso><DescricaoIdentificacaoMateria>PL 2450/2019</DescricaoIdentificacaoMateria></IdentificacaoMateria><EmentaMateria>Altera a Lei nº 11.340, de 7 de agosto de 2006, para prever que a intimação das medidas protetivas de urgência previstas nos incisos I, II e III do art. 22 possa ser entregue pelo defensor da ofendida ou pelo agente policial.</EmentaMateria></Materia><Materia><IdentificacaoMateria><CodigoMateria>136421</CodigoMateria><SiglaCasaIdentificacaoMateria>SF</SiglaCasaIdentificacaoMateria><NomeCasaIdentificacaoMateria>Senado Federal</NomeCasaIdentificacaoMateria><SiglaSubtipoMateria>PL</SiglaSubtipoMateria><DescricaoSubtipoMateria>PROJETO DE LEI</DescricaoSubtipoMateria><NumeroMateria>02452</NumeroMateria><AnoMateria>2019</AnoMateria><DescricaoObjetivoProcesso>Iniciadora</DescricaoObjetivoProcesso><DescricaoIdentificacaoMateria>PL 2452/2019</DescricaoIdentificacaoMateria></IdentificacaoMateria><EmentaMateria>Acrescenta §§ 2º e 3º ao art. 1.575 da Lei nº 10.406, de 10 de janeiro de 2002, para dispor sobre a fraude na partilha de bens por dissolução do casamento.</EmentaMateria></Materia><Materia><IdentificacaoMateria><CodigoMateria>136711</CodigoMateria><SiglaCasaIdentificacaoMateria>SF</SiglaCasaIdentificacaoMateria><NomeCasaIdentificacaoMateria>Senado Federal</NomeCasaIdentificacaoMateria><SiglaSubtipoMateria>REQ</SiglaSubtipoMateria><DescricaoSubtipoMateria>REQUERIMENTO</DescricaoSubtipoMateria><NumeroMateria>00048</NumeroMateria><AnoMateria>2019</AnoMateria><SiglaComissaoRequerimento>CDH</SiglaComissaoRequerimento><DescricaoIdentificacaoMateria>REQ 48/2019 - CDH</DescricaoIdentificacaoMateria></IdentificacaoMateria><EmentaMateria>Requer, nos termos do art. 73 do Regimento Interno do Senado Federal, a criação de Subcomissão Temporária, composta de 5 (cinco) membros titulares e igual número de suplentes, para, no prazo de 210 (duzentos e dez) dias, debater questões relacionadas ao sistema penitenciário brasileiro.</EmentaMateria></Materia><Materia><IdentificacaoMateria><CodigoMateria>136742</CodigoMateria><SiglaCasaIdentificacaoMateria>SF</SiglaCasaIdentificacaoMateria><NomeCasaIdentificacaoMateria>Senado Federal</NomeCasaIdentificacaoMateria><SiglaSubtipoMateria>PEC</SiglaSubtipoMateria><DescricaoSubtipoMateria>PROPOSTA DE EMENDA À CONSTITUIÇÃO</DescricaoSubtipoMateria><NumeroMateria>00071</NumeroMateria><AnoMateria>2019</AnoMateria><DescricaoObjetivoProcesso>Iniciadora</DescricaoObjetivoProcesso><DescricaoIdentificacaoMateria>PEC 71/2019</DescricaoIdentificacaoMateria></IdentificacaoMateria><EmentaMateria>Altera o § 9º do art. 37 da Constituição Federal, para submeter ao teto remuneratório as entidades privadas sem fins lucrativos mantidas com contribuições parafiscais ou que recebam recursos públicos para o pagamento de despesas de pessoal ou de custeio em geral.</EmentaMateria></Materia><Materia><IdentificacaoMateria><CodigoMateria>137004</CodigoMateria><SiglaCasaIdentificacaoMateria>SF</SiglaCasaIdentificacaoMateria><NomeCasaIdentificacaoMateria>Senado Federal</NomeCasaIdentificacaoMateria><SiglaSubtipoMateria>PL</SiglaSubtipoMateria><DescricaoSubtipoMateria>PROJETO DE LEI</DescricaoSubtipoMateria><NumeroMateria>03167</NumeroMateria><AnoMateria>2019</AnoMateria><DescricaoObjetivoProcesso>Iniciadora</DescricaoObjetivoProcesso><DescricaoIdentificacaoMateria>PL 3167/2019</DescricaoIdentificacaoMateria></IdentificacaoMateria><EmentaMateria>Altera os arts. 94, 96, 97, 98 e 99 da Lei no 10.741, de 1º de outubro 2003, para aumentar as penas para os crimes de discriminação, falta de assistência, abandono e exposição a perigo contra o idoso, e para adotar a regra geral para aplicação do procedimento sumaríssimo.</EmentaMateria></Materia><Materia><IdentificacaoMateria><CodigoMateria>137316</CodigoMateria><SiglaCasaIdentificacaoMateria>SF</SiglaCasaIdentificacaoMateria><NomeCasaIdentificacaoMateria>Senado Federal</NomeCasaIdentificacaoMateria><SiglaSubtipoMateria>REQ</SiglaSubtipoMateria><DescricaoSubtipoMateria>REQUERIMENTO</DescricaoSubtipoMateria><NumeroMateria>00073</NumeroMateria><AnoMateria>2019</AnoMateria><SiglaComissaoRequerimento>CDH</SiglaComissaoRequerimento><DescricaoIdentificacaoMateria>REQ 73/2019 - CDH</DescricaoIdentificacaoMateria></IdentificacaoMateria><EmentaMateria>Requer, nos termos do art. 93, I, do Regimento Interno do Senado Federal, a realização de audiência pública, em conjunto com a Comissão de Assuntos Sociais, com o objetivo de instruir o PLS 366/2017, que revoga os arts. 477-A e 477- B da Consolidação das Leis do Trabalho, aprovada pelo Decreto-Lei nº 5.452, de 1º de maio de 1943, com a redação dada pela Lei nº 13.467, de 13 de julho de 2017.</EmentaMateria></Materia><Materia><IdentificacaoMateria><CodigoMateria>137498</CodigoMateria><SiglaCasaIdentificacaoMateria>SF</SiglaCasaIdentificacaoMateria><NomeCasaIdentificacaoMateria>Senado Federal</NomeCasaIdentificacaoMateria><SiglaSubtipoMateria>PL</SiglaSubtipoMateria><DescricaoSubtipoMateria>PROJETO DE LEI</DescricaoSubtipoMateria><NumeroMateria>03799</NumeroMateria><AnoMateria>2019</AnoMateria><DescricaoObjetivoProcesso>Iniciadora</DescricaoObjetivoProcesso><DescricaoIdentificacaoMateria>PL 3799/2019</DescricaoIdentificacaoMateria></IdentificacaoMateria><EmentaMateria>Altera o Livro V da Parte Especial da Lei nº 10.406, de 10 de janeiro de 2002, e o Título III do Livro I da Parte Especial da Lei nº 13.105, de 16 de março de 2015, para dispor sobre a sucessão em geral, a sucessão legítima, a sucessão testamentária, o inventário e a partilha.</EmentaMateria></Materia><Materia><IdentificacaoMateria><CodigoMateria>138474</CodigoMateria><SiglaCasaIdentificacaoMateria>SF</SiglaCasaIdentificacaoMateria><NomeCasaIdentificacaoMateria>Senado Federal</NomeCasaIdentificacaoMateria><SiglaSubtipoMateria>PL</SiglaSubtipoMateria><DescricaoSubtipoMateria>PROJETO DE LEI</DescricaoSubtipoMateria><NumeroMateria>04807</NumeroMateria><AnoMateria>2019</AnoMateria><DescricaoObjetivoProcesso>Iniciadora</DescricaoObjetivoProcesso><DescricaoIdentificacaoMateria>PL 4807/2019</DescricaoIdentificacaoMateria></IdentificacaoMateria><EmentaMateria>Disciplina a comercialização de produtos no ambiente da internet para obrigar o fornecedor a divulgar as condições integrais da oferta, inclusive sobre a indisponibilidade do produto em território nacional.</EmentaMateria></Materia><Materia><IdentificacaoMateria><CodigoMateria>138491</CodigoMateria><SiglaCasaIdentificacaoMateria>SF</SiglaCasaIdentificacaoMateria><NomeCasaIdentificacaoMateria>Senado Federal</NomeCasaIdentificacaoMateria><SiglaSubtipoMateria>PRS</SiglaSubtipoMateria><DescricaoSubtipoMateria>PROJETO DE RESOLUÇÃO DO SENADO</DescricaoSubtipoMateria><NumeroMateria>00080</NumeroMateria><AnoMateria>2019</AnoMateria><DescricaoIdentificacaoMateria>PRS 80/2019</DescricaoIdentificacaoMateria></IdentificacaoMateria><EmentaMateria>Cria o Programa Mulher Senadora no âmbito do Senado Federal.</EmentaMateria></Materia><Materia><IdentificacaoMateria><CodigoMateria>138664</CodigoMateria><SiglaCasaIdentificacaoMateria>SF</SiglaCasaIdentificacaoMateria><NomeCasaIdentificacaoMateria>Senado Federal</NomeCasaIdentificacaoMateria><SiglaSubtipoMateria>PL</SiglaSubtipoMateria><DescricaoSubtipoMateria>PROJETO DE LEI</DescricaoSubtipoMateria><NumeroMateria>04971</NumeroMateria><AnoMateria>2019</AnoMateria><DescricaoObjetivoProcesso>Iniciadora</DescricaoObjetivoProcesso><DescricaoIdentificacaoMateria>PL 4971/2019</DescricaoIdentificacaoMateria></IdentificacaoMateria><EmentaMateria>Altera a Lei nº 8.906, de 04 de julho de 1994, que dispõe sobre o Estatuto da Advocacia e a Ordem dos Advogados do Brasil (OAB), para estabelecer eleições diretas para a Diretoria do Conselho Federal da OAB.</EmentaMateria></Materia><Materia><IdentificacaoMateria><CodigoMateria>138675</CodigoMateria><SiglaCasaIdentificacaoMateria>SF</SiglaCasaIdentificacaoMateria><NomeCasaIdentificacaoMateria>Senado Federal</NomeCasaIdentificacaoMateria><SiglaSubtipoMateria>PL</SiglaSubtipoMateria><DescricaoSubtipoMateria>PROJETO DE LEI</DescricaoSubtipoMateria><NumeroMateria>04975</NumeroMateria><AnoMateria>2019</AnoMateria><DescricaoObjetivoProcesso>Iniciadora</DescricaoObjetivoProcesso><DescricaoIdentificacaoMateria>PL 4975/2019</DescricaoIdentificacaoMateria></IdentificacaoMateria><EmentaMateria>Altera da Lei nº 4.737, de 15 de julho de 1965 – Código Eleitoral, para redimensionar a pena do crime previsto no § 3º do art. 326-A.</EmentaMateria></Materia><Materia><IdentificacaoMateria><CodigoMateria>138678</CodigoMateria><SiglaCasaIdentificacaoMateria>SF</SiglaCasaIdentificacaoMateria><NomeCasaIdentificacaoMateria>Senado Federal</NomeCasaIdentificacaoMateria><SiglaSubtipoMateria>PL</SiglaSubtipoMateria><DescricaoSubtipoMateria>PROJETO DE LEI</DescricaoSubtipoMateria><NumeroMateria>04970</NumeroMateria><AnoMateria>2019</AnoMateria><DescricaoObjetivoProcesso>Iniciadora</DescricaoObjetivoProcesso><DescricaoIdentificacaoMateria>PL 4970/2019</DescricaoIdentificacaoMateria></IdentificacaoMateria><EmentaMateria>Altera o art. 37 da Lei nº 9.492, de 10 de setembro de 1997, para diferir o pagamento dos emolumentos devidos pelo protesto de títulos.</EmentaMateria></Materia><Materia><IdentificacaoMateria><CodigoMateria>138985</CodigoMateria><SiglaCasaIdentificacaoMateria>SF</SiglaCasaIdentificacaoMateria><NomeCasaIdentificacaoMateria>Senado Federal</NomeCasaIdentificacaoMateria><SiglaSubtipoMateria>RQS</SiglaSubtipoMateria><DescricaoSubtipoMateria>REQUERIMENTO</DescricaoSubtipoMateria><NumeroMateria>00815</NumeroMateria><AnoMateria>2019</AnoMateria><DescricaoIdentificacaoMateria>RQS 815/2019</DescricaoIdentificacaoMateria></IdentificacaoMateria><EmentaMateria>Oitiva da Comissão de Assuntos Sociais sobre o Projeto de Lei nº 2709, de 2019.</EmentaMateria></Materia><Materia><IdentificacaoMateria><CodigoMateria>139689</CodigoMateria><SiglaCasaIdentificacaoMateria>SF</SiglaCasaIdentificacaoMateria><NomeCasaIdentificacaoMateria>Senado Federal</NomeCasaIdentificacaoMateria><SiglaSubtipoMateria>PL</SiglaSubtipoMateria><DescricaoSubtipoMateria>PROJETO DE LEI</DescricaoSubtipoMateria><NumeroMateria>05833</NumeroMateria><AnoMateria>2019</AnoMateria><DescricaoObjetivoProcesso>Iniciadora</DescricaoObjetivoProcesso><DescricaoIdentificacaoMateria>PL 5833/2019</DescricaoIdentificacaoMateria></IdentificacaoMateria><EmentaMateria>Dispõe sobre o serviço de retransmissão de televisão e altera a Lei nº 4.117, de 27 de agosto de 1962, que institui o Código Brasileiro de Telecomunicações, para estabelecer a obrigatoriedade da retransmissão diária de informações oficiais dos Poderes da República pelos canais de televisão aberta.</EmentaMateria></Materia><Materia><IdentificacaoMateria><CodigoMateria>139962</CodigoMateria><SiglaCasaIdentificacaoMateria>SF</SiglaCasaIdentificacaoMateria><NomeCasaIdentificacaoMateria>Senado Federal</NomeCasaIdentificacaoMateria><SiglaSubtipoMateria>PL</SiglaSubtipoMateria><DescricaoSubtipoMateria>PROJETO DE LEI</DescricaoSubtipoMateria><NumeroMateria>06202</NumeroMateria><AnoMateria>2019</AnoMateria><DescricaoObjetivoProcesso>Iniciadora</DescricaoObjetivoProcesso><DescricaoIdentificacaoMateria>PL 6202/2019</DescricaoIdentificacaoMateria></IdentificacaoMateria><EmentaMateria>Altera o Decreto-Lei nº 3.689, de 03 de outubro de 1941 – Código de Processo Penal, para dispor sobre a decretação da prisão preventiva para garantia da ordem pública, quando confirmada por tribunal competente a sentença penal condenatória que fixar pena privativa de liberdade igual ou superior a oito anos de reclusão.</EmentaMateria></Materia><Materia><IdentificacaoMateria><CodigoMateria>139971</CodigoMateria><SiglaCasaIdentificacaoMateria>SF</SiglaCasaIdentificacaoMateria><NomeCasaIdentificacaoMateria>Senado Federal</NomeCasaIdentificacaoMateria><SiglaSubtipoMateria>PL</SiglaSubtipoMateria><DescricaoSubtipoMateria>PROJETO DE LEI</DescricaoSubtipoMateria><NumeroMateria>06204</NumeroMateria><AnoMateria>2019</AnoMateria><DescricaoObjetivoProcesso>Iniciadora</DescricaoObjetivoProcesso><DescricaoIdentificacaoMateria>PL 6204/2019</DescricaoIdentificacaoMateria></IdentificacaoMateria><EmentaMateria>Dispõe sobre a desjudicialização da execução civil de título executivo judicial e extrajudicial; altera as Leis nª a nº 9.430, de 27 de dezembro de 1996, a nº 9.492, de 10 de setembro de 1997, a nº 10.169, de 29 de dezembro de 2000, e a nº 13.105 de 16 de março de 2015 – Código de Processo Civil.</EmentaMateria></Materia><Materia><IdentificacaoMateria><CodigoMateria>140082</CodigoMateria><SiglaCasaIdentificacaoMateria>SF</SiglaCasaIdentificacaoMateria><NomeCasaIdentificacaoMateria>Senado Federal</NomeCasaIdentificacaoMateria><SiglaSubtipoMateria>REQ</SiglaSubtipoMateria><DescricaoSubtipoMateria>REQUERIMENTO</DescricaoSubtipoMateria><NumeroMateria>00035</NumeroMateria><AnoMateria>2019</AnoMateria><SiglaComissaoRequerimento>CRA</SiglaComissaoRequerimento><DescricaoIdentificacaoMateria>REQ 35/2019 - CRA</DescricaoIdentificacaoMateria></IdentificacaoMateria><EmentaMateria>Requeiro, nos termos do art. 58, § 2º, II, da Constituição Federal e do art. 93, II, do Regimento Interno do Senado Federal, a realização de audiência pública, em conjunto com a Comissão de Ciência, Tecnologia, Inovação, Comunicação e Informática, com o objetivo de debater a conectividade no campo. Proponho para a audiência a presença dos seguintes convidados:
      • Representante do Ministério da Agricultura, Pecuária e Abastecimento (MAPA);
      • Representante do Ministério da Ciência, Tecnologia, Inovações e Comunicações (MCTIC);
      • Representante da Confederação Nacional da Agricultura e Pecuária (CNA);
      • Representante da Organização das Cooperativas Brasileiras (OCB); e
      • Representante da Agência Nacional de Telecomunicações (Anatel).</EmentaMateria></Materia><Materia><IdentificacaoMateria><CodigoMateria>140244</CodigoMateria><SiglaCasaIdentificacaoMateria>SF</SiglaCasaIdentificacaoMateria><NomeCasaIdentificacaoMateria>Senado Federal</NomeCasaIdentificacaoMateria><SiglaSubtipoMateria>PL</SiglaSubtipoMateria><DescricaoSubtipoMateria>PROJETO DE LEI</DescricaoSubtipoMateria><NumeroMateria>06469</NumeroMateria><AnoMateria>2019</AnoMateria><DescricaoObjetivoProcesso>Iniciadora</DescricaoObjetivoProcesso><DescricaoIdentificacaoMateria>PL 6469/2019</DescricaoIdentificacaoMateria></IdentificacaoMateria><EmentaMateria>Regulamenta a profissão do Profissional Instrutor de Pilates e seu exercício.</EmentaMateria></Materia></MateriasDeAutoriaTramitando><RelatoriasAtuais><Relatoria><Materia><IdentificacaoMateria><CodigoMateria>107517</CodigoMateria><SiglaCasaIdentificacaoMateria>SF</SiglaCasaIdentificacaoMateria><NomeCasaIdentificacaoMateria>Senado Federal</NomeCasaIdentificacaoMateria><SiglaSubtipoMateria>PLS</SiglaSubtipoMateria><DescricaoSubtipoMateria>PROJETO DE LEI DO SENADO</DescricaoSubtipoMateria><NumeroMateria>00349</NumeroMateria><AnoMateria>2012</AnoMateria></IdentificacaoMateria><EmentaMateria>Altera a Lei nº 10.098, de 19 de dezembro de 2000, para tratar do fornecimento, pelas instituições financeiras e operadoras de cartão de crédito, de serviços ao consumidor portador de deficiência visual.</EmentaMateria></Materia><IdentificacaoComissao><CodigoComissao>834</CodigoComissao><SiglaComissao>CDH</SiglaComissao><NomeComissao>Comissão de Direitos Humanos e Legislação Participativa</NomeComissao><SiglaCasaComissao>SF</SiglaCasaComissao><NomeCasaComissao>Senado Federal</NomeCasaComissao></IdentificacaoComissao><DescricaoTipoRelator>Relator</DescricaoTipoRelator><DataDesignacao>2019-04-24</DataDesignacao></Relatoria><Relatoria><Materia><IdentificacaoMateria><CodigoMateria>115437</CodigoMateria><SiglaCasaIdentificacaoMateria>SF</SiglaCasaIdentificacaoMateria><NomeCasaIdentificacaoMateria>Senado Federal</NomeCasaIdentificacaoMateria><SiglaSubtipoMateria>PLS</SiglaSubtipoMateria><DescricaoSubtipoMateria>PROJETO DE LEI DO SENADO</DescricaoSubtipoMateria><NumeroMateria>00487</NumeroMateria><AnoMateria>2013</AnoMateria></IdentificacaoMateria><EmentaMateria>Reforma o Código Comercial.</EmentaMateria></Materia><IdentificacaoComissao><CodigoComissao>2294</CodigoComissao><SiglaComissao>CTRCC</SiglaComissao><NomeComissao>Comissão Temporária para Reforma do Código Comercial (Art. 374-RISF) - 2019</NomeComissao><SiglaCasaComissao>SF</SiglaCasaComissao><NomeCasaComissao>Senado Federal</NomeCasaComissao></IdentificacaoComissao><DescricaoTipoRelator>Relator</DescricaoTipoRelator><DataDesignacao>2019-12-17</DataDesignacao></Relatoria><Relatoria><Materia><IdentificacaoMateria><CodigoMateria>121989</CodigoMateria><SiglaCasaIdentificacaoMateria>SF</SiglaCasaIdentificacaoMateria><NomeCasaIdentificacaoMateria>Senado Federal</NomeCasaIdentificacaoMateria><SiglaSubtipoMateria>PLS</SiglaSubtipoMateria><DescricaoSubtipoMateria>PROJETO DE LEI DO SENADO</DescricaoSubtipoMateria><NumeroMateria>00396</NumeroMateria><AnoMateria>2015</AnoMateria></IdentificacaoMateria><EmentaMateria>Altera o art. 32 da Lei nº 9.605, de 12 de fevereiro de 1998, para aumentar a pena do crime de maus-tratos contra animais.</EmentaMateria></Materia><IdentificacaoComissao><CodigoComissao>50</CodigoComissao><SiglaComissao>CMA</SiglaComissao><NomeComissao>Comissão de Meio Ambiente</NomeComissao><SiglaCasaComissao>SF</SiglaCasaComissao><NomeCasaComissao>Senado Federal</NomeCasaComissao></IdentificacaoComissao><DescricaoTipoRelator>Relator</DescricaoTipoRelator><DataDesignacao>2020-08-03</DataDesignacao></Relatoria><Relatoria><Materia><IdentificacaoMateria><CodigoMateria>124329</CodigoMateria><SiglaCasaIdentificacaoMateria>SF</SiglaCasaIdentificacaoMateria><NomeCasaIdentificacaoMateria>Senado Federal</NomeCasaIdentificacaoMateria><SiglaSubtipoMateria>PLS</SiglaSubtipoMateria><DescricaoSubtipoMateria>PROJETO DE LEI DO SENADO</DescricaoSubtipoMateria><NumeroMateria>00765</NumeroMateria><AnoMateria>2015</AnoMateria></IdentificacaoMateria><EmentaMateria>Acrescenta o art. 22-A à Lei nº 12.846, de 1º de agosto de 2013, para instituir o Fundo Nacional de Combate à Corrupção – FNCC.</EmentaMateria></Materia><IdentificacaoComissao><CodigoComissao>34</CodigoComissao><SiglaComissao>CCJ</SiglaComissao><NomeComissao>Comissão de Constituição, Justiça e Cidadania</NomeComissao><SiglaCasaComissao>SF</SiglaCasaComissao><NomeCasaComissao>Senado Federal</NomeCasaComissao></IdentificacaoComissao><DescricaoTipoRelator>Relator</DescricaoTipoRelator><DataDesignacao>2020-03-11</DataDesignacao></Relatoria><Relatoria><Materia><IdentificacaoMateria><CodigoMateria>127806</CodigoMateria><SiglaCasaIdentificacaoMateria>SF</SiglaCasaIdentificacaoMateria><NomeCasaIdentificacaoMateria>Senado Federal</NomeCasaIdentificacaoMateria><SiglaSubtipoMateria>PLS</SiglaSubtipoMateria><DescricaoSubtipoMateria>PROJETO DE LEI DO SENADO</DescricaoSubtipoMateria><NumeroMateria>00466</NumeroMateria><AnoMateria>2016</AnoMateria></IdentificacaoMateria><EmentaMateria>Dispõe sobre a instituição do Dia Nacional do Oficial do Ministério Público.</EmentaMateria></Materia><IdentificacaoComissao><CodigoComissao>47</CodigoComissao><SiglaComissao>CE</SiglaComissao><NomeComissao>Comissão de Educação, Cultura e Esporte</NomeComissao><SiglaCasaComissao>SF</SiglaCasaComissao><NomeCasaComissao>Senado Federal</NomeCasaComissao></IdentificacaoComissao><DescricaoTipoRelator>Relator</DescricaoTipoRelator><DataDesignacao>2019-10-09</DataDesignacao></Relatoria><Relatoria><Materia><IdentificacaoMateria><CodigoMateria>128912</CodigoMateria><SiglaCasaIdentificacaoMateria>SF</SiglaCasaIdentificacaoMateria><NomeCasaIdentificacaoMateria>Senado Federal</NomeCasaIdentificacaoMateria><SiglaSubtipoMateria>PLS</SiglaSubtipoMateria><DescricaoSubtipoMateria>PROJETO DE LEI DO SENADO</DescricaoSubtipoMateria><NumeroMateria>00123</NumeroMateria><AnoMateria>2017</AnoMateria></IdentificacaoMateria><EmentaMateria>Concede anistia aos ex-empregados de Empresas Públicas e Sociedades de Economia Mista, demitidos sem justa causa</EmentaMateria></Materia><IdentificacaoComissao><CodigoComissao>34</CodigoComissao><SiglaComissao>CCJ</SiglaComissao><NomeComissao>Comissão de Constituição, Justiça e Cidadania</NomeComissao><SiglaCasaComissao>SF</SiglaCasaComissao><NomeCasaComissao>Senado Federal</NomeCasaComissao></IdentificacaoComissao><DescricaoTipoRelator>Relator</DescricaoTipoRelator><DataDesignacao>2020-02-06</DataDesignacao></Relatoria><Relatoria><Materia><IdentificacaoMateria><CodigoMateria>129217</CodigoMateria><SiglaCasaIdentificacaoMateria>SF</SiglaCasaIdentificacaoMateria><NomeCasaIdentificacaoMateria>Senado Federal</NomeCasaIdentificacaoMateria><SiglaSubtipoMateria>PLS</SiglaSubtipoMateria><DescricaoSubtipoMateria>PROJETO DE LEI DO SENADO</DescricaoSubtipoMateria><NumeroMateria>00151</NumeroMateria><AnoMateria>2017</AnoMateria></IdentificacaoMateria><EmentaMateria>Altera os arts. 392, 392-A e 473, III da Consolidação das Leis do Trabalho (CLT), aprovada pelo Decreto-Lei nº 5.452, de 1º de maio de 1943, para estabelecer o compartilhamento da licença maternidade e da licença adotante.</EmentaMateria></Materia><IdentificacaoComissao><CodigoComissao>40</CodigoComissao><SiglaComissao>CAS</SiglaComissao><NomeComissao>Comissão de Assuntos Sociais</NomeComissao><SiglaCasaComissao>SF</SiglaCasaComissao><NomeCasaComissao>Senado Federal</NomeCasaComissao></IdentificacaoComissao><DescricaoTipoRelator>Relator</DescricaoTipoRelator><DataDesignacao>2019-02-21</DataDesignacao></Relatoria><Relatoria><Materia><IdentificacaoMateria><CodigoMateria>130164</CodigoMateria><SiglaCasaIdentificacaoMateria>SF</SiglaCasaIdentificacaoMateria><NomeCasaIdentificacaoMateria>Senado Federal</NomeCasaIdentificacaoMateria><SiglaSubtipoMateria>PLS</SiglaSubtipoMateria><DescricaoSubtipoMateria>PROJETO DE LEI DO SENADO</DescricaoSubtipoMateria><NumeroMateria>00236</NumeroMateria><AnoMateria>2017</AnoMateria></IdentificacaoMateria><EmentaMateria>Acrescenta o Capitulo V ao Título III da Consolidação das Leis do Trabalho (CLT), aprovada pelo Decreto-Lei nº 5.452, de 1º de maio de 1943, para dispor sobre a proteção do trabalho do idoso, e acrescenta o § 16 ao art. 22 da Lei nº 8.212, de 24 de julho de 1991, para dispor sobre incentivo à contratação de empregados com mais de cinquenta e cinco anos de idade</EmentaMateria></Materia><IdentificacaoComissao><CodigoComissao>40</CodigoComissao><SiglaComissao>CAS</SiglaComissao><NomeComissao>Comissão de Assuntos Sociais</NomeComissao><SiglaCasaComissao>SF</SiglaCasaComissao><NomeCasaComissao>Senado Federal</NomeCasaComissao></IdentificacaoComissao><DescricaoTipoRelator>Relator</DescricaoTipoRelator><DataDesignacao>2019-02-21</DataDesignacao></Relatoria><Relatoria><Materia><IdentificacaoMateria><CodigoMateria>130205</CodigoMateria><SiglaCasaIdentificacaoMateria>SF</SiglaCasaIdentificacaoMateria><NomeCasaIdentificacaoMateria>Senado Federal</NomeCasaIdentificacaoMateria><SiglaSubtipoMateria>SUG</SiglaSubtipoMateria><DescricaoSubtipoMateria>SUGESTÃO</DescricaoSubtipoMateria><NumeroMateria>00031</NumeroMateria><AnoMateria>2017</AnoMateria></IdentificacaoMateria><EmentaMateria>Um Salário para honrar a profissão do Nutricionista</EmentaMateria></Materia><IdentificacaoComissao><CodigoComissao>834</CodigoComissao><SiglaComissao>CDH</SiglaComissao><NomeComissao>Comissão de Direitos Humanos e Legislação Participativa</NomeComissao><SiglaCasaComissao>SF</SiglaCasaComissao><NomeCasaComissao>Senado Federal</NomeCasaComissao></IdentificacaoComissao><DescricaoTipoRelator>Relator</DescricaoTipoRelator><DataDesignacao>2019-02-26</DataDesignacao></Relatoria><Relatoria><Materia><IdentificacaoMateria><CodigoMateria>130527</CodigoMateria><SiglaCasaIdentificacaoMateria>SF</SiglaCasaIdentificacaoMateria><NomeCasaIdentificacaoMateria>Senado Federal</NomeCasaIdentificacaoMateria><SiglaSubtipoMateria>PLS</SiglaSubtipoMateria><DescricaoSubtipoMateria>PROJETO DE LEI DO SENADO</DescricaoSubtipoMateria><NumeroMateria>00298</NumeroMateria><AnoMateria>2017</AnoMateria></IdentificacaoMateria><EmentaMateria>Revoga o parágrafo único do art. 60 da Consolidação das Leis do Trabalho (CLT), aprovada pelo Decreto-Lei nº 5.452, de 1º de maio de 1943, que dispensa de licença prévia a adoção de jornada de doze horas de trabalho por trinta e seis horas ininterruptas de descanso</EmentaMateria></Materia><IdentificacaoComissao><CodigoComissao>40</CodigoComissao><SiglaComissao>CAS</SiglaComissao><NomeComissao>Comissão de Assuntos Sociais</NomeComissao><SiglaCasaComissao>SF</SiglaCasaComissao><NomeCasaComissao>Senado Federal</NomeCasaComissao></IdentificacaoComissao><DescricaoTipoRelator>Relator</DescricaoTipoRelator><DataDesignacao>2019-12-03</DataDesignacao></Relatoria><Relatoria><Materia><IdentificacaoMateria><CodigoMateria>131857</CodigoMateria><SiglaCasaIdentificacaoMateria>SF</SiglaCasaIdentificacaoMateria><NomeCasaIdentificacaoMateria>Senado Federal</NomeCasaIdentificacaoMateria><SiglaSubtipoMateria>PLS</SiglaSubtipoMateria><DescricaoSubtipoMateria>PROJETO DE LEI DO SENADO</DescricaoSubtipoMateria><NumeroMateria>00490</NumeroMateria><AnoMateria>2017</AnoMateria></IdentificacaoMateria><EmentaMateria>Altera a Lei nº 9.394, de 20 de dezembro de 1996, que estabelece as diretrizes e bases da educação nacional, e a Lei nº 8.069, de 13 de julho de 1990, que dispõe sobre o Estatuto da Criança e do Adolescente, para prever a modalidade da educação domiciliar no âmbito da educação básica.</EmentaMateria></Materia><IdentificacaoComissao><CodigoComissao>834</CodigoComissao><SiglaComissao>CDH</SiglaComissao><NomeComissao>Comissão de Direitos Humanos e Legislação Participativa</NomeComissao><SiglaCasaComissao>SF</SiglaCasaComissao><NomeCasaComissao>Senado Federal</NomeCasaComissao></IdentificacaoComissao><DescricaoTipoRelator>Relator</DescricaoTipoRelator><DataDesignacao>2019-02-19</DataDesignacao></Relatoria><Relatoria><Materia><IdentificacaoMateria><CodigoMateria>132215</CodigoMateria><SiglaCasaIdentificacaoMateria>SF</SiglaCasaIdentificacaoMateria><NomeCasaIdentificacaoMateria>Senado Federal</NomeCasaIdentificacaoMateria><SiglaSubtipoMateria>PLS</SiglaSubtipoMateria><DescricaoSubtipoMateria>PROJETO DE LEI DO SENADO</DescricaoSubtipoMateria><NumeroMateria>00041</NumeroMateria><AnoMateria>2018</AnoMateria></IdentificacaoMateria><EmentaMateria>Altera o Decreto-Lei nº 5.452, de 1º de maio de 1943, que dispõe sobre a Consolidação das Leis do Trabalho, para estabelecer proteção especial a determinados grupos de trabalhadores na adesão a planos de demissão voluntária ou incentivada.</EmentaMateria></Materia><IdentificacaoComissao><CodigoComissao>40</CodigoComissao><SiglaComissao>CAS</SiglaComissao><NomeComissao>Comissão de Assuntos Sociais</NomeComissao><SiglaCasaComissao>SF</SiglaCasaComissao><NomeCasaComissao>Senado Federal</NomeCasaComissao></IdentificacaoComissao><DescricaoTipoRelator>Relator</DescricaoTipoRelator><DataDesignacao>2019-03-13</DataDesignacao></Relatoria><Relatoria><Materia><IdentificacaoMateria><CodigoMateria>132411</CodigoMateria><SiglaCasaIdentificacaoMateria>SF</SiglaCasaIdentificacaoMateria><NomeCasaIdentificacaoMateria>Senado Federal</NomeCasaIdentificacaoMateria><SiglaSubtipoMateria>PLC</SiglaSubtipoMateria><DescricaoSubtipoMateria>PROJETO DE LEI DA CÂMARA</DescricaoSubtipoMateria><NumeroMateria>00010</NumeroMateria><AnoMateria>2018</AnoMateria></IdentificacaoMateria><EmentaMateria>Disciplina o aproveitamento de carcaças de animais de produção e de outros resíduos animais no campo para fins agropecuários e industriais.</EmentaMateria></Materia><IdentificacaoComissao><CodigoComissao>50</CodigoComissao><SiglaComissao>CMA</SiglaComissao><NomeComissao>Comissão de Meio Ambiente</NomeComissao><SiglaCasaComissao>SF</SiglaCasaComissao><NomeCasaComissao>Senado Federal</NomeCasaComissao></IdentificacaoComissao><DescricaoTipoRelator>Relator</DescricaoTipoRelator><DataDesignacao>2019-02-21</DataDesignacao></Relatoria><Relatoria><Materia><IdentificacaoMateria><CodigoMateria>134281</CodigoMateria><SiglaCasaIdentificacaoMateria>SF</SiglaCasaIdentificacaoMateria><NomeCasaIdentificacaoMateria>Senado Federal</NomeCasaIdentificacaoMateria><SiglaSubtipoMateria>PLS</SiglaSubtipoMateria><DescricaoSubtipoMateria>PROJETO DE LEI DO SENADO</DescricaoSubtipoMateria><NumeroMateria>00398</NumeroMateria><AnoMateria>2018</AnoMateria></IdentificacaoMateria><EmentaMateria>Altera a Lei nº 9.394, de 20 de dezembro de 1996, que “estabelece as diretrizes e bases da educação nacional”, e a Lei nº 10.973, de 2 de dezembro de 2004, que “dispõe sobre incentivos à inovação e à pesquisa científica e tecnológica no ambiente produtivo e dá outras providências”, para dispor sobre estímulo à participação feminina nas áreas de ciência, tecnologia, engenharia e matemática, e mitigação de barreiras contra mulheres nessas áreas.</EmentaMateria></Materia><IdentificacaoComissao><CodigoComissao>834</CodigoComissao><SiglaComissao>CDH</SiglaComissao><NomeComissao>Comissão de Direitos Humanos e Legislação Participativa</NomeComissao><SiglaCasaComissao>SF</SiglaCasaComissao><NomeCasaComissao>Senado Federal</NomeCasaComissao></IdentificacaoComissao><DescricaoTipoRelator>Relator</DescricaoTipoRelator><DataDesignacao>2019-02-20</DataDesignacao></Relatoria><Relatoria><Materia><IdentificacaoMateria><CodigoMateria>134300</CodigoMateria><SiglaCasaIdentificacaoMateria>SF</SiglaCasaIdentificacaoMateria><NomeCasaIdentificacaoMateria>Senado Federal</NomeCasaIdentificacaoMateria><SiglaSubtipoMateria>PLS</SiglaSubtipoMateria><DescricaoSubtipoMateria>PROJETO DE LEI DO SENADO</DescricaoSubtipoMateria><NumeroMateria>00406</NumeroMateria><AnoMateria>2018</AnoMateria></IdentificacaoMateria><EmentaMateria>Altera a Lei nº 9.263, de 12 de janeiro de 1996, que regula o § 7º do art. 226 da Constituição Federal, que trata do planejamento familiar, estabelece penalidades e dá outras providências, para revogar as exigências que desencorajam a opção pela esterilização cirúrgica como método contraceptivo e impõem dificuldades para a realização do procedimento nos serviços de saúde.</EmentaMateria></Materia><IdentificacaoComissao><CodigoComissao>40</CodigoComissao><SiglaComissao>CAS</SiglaComissao><NomeComissao>Comissão de Assuntos Sociais</NomeComissao><SiglaCasaComissao>SF</SiglaCasaComissao><NomeCasaComissao>Senado Federal</NomeCasaComissao></IdentificacaoComissao><DescricaoTipoRelator>Relator</DescricaoTipoRelator><DataDesignacao>2019-08-22</DataDesignacao></Relatoria><Relatoria><Materia><IdentificacaoMateria><CodigoMateria>134864</CodigoMateria><SiglaCasaIdentificacaoMateria>SF</SiglaCasaIdentificacaoMateria><NomeCasaIdentificacaoMateria>Senado Federal</NomeCasaIdentificacaoMateria><SiglaSubtipoMateria>PLS</SiglaSubtipoMateria><DescricaoSubtipoMateria>PROJETO DE LEI DO SENADO</DescricaoSubtipoMateria><NumeroMateria>00520</NumeroMateria><AnoMateria>2018</AnoMateria></IdentificacaoMateria><EmentaMateria>Altera a redação do art. 49 da Lei 9.394, de 20 de dezembro de 1996, para dispor sobre aproveitamento de disciplinas cursadas com aprovação, na educação de nível superior.</EmentaMateria></Materia><IdentificacaoComissao><CodigoComissao>47</CodigoComissao><SiglaComissao>CE</SiglaComissao><NomeComissao>Comissão de Educação, Cultura e Esporte</NomeComissao><SiglaCasaComissao>SF</SiglaCasaComissao><NomeCasaComissao>Senado Federal</NomeCasaComissao></IdentificacaoComissao><DescricaoTipoRelator>Relator</DescricaoTipoRelator><DataDesignacao>2019-03-27</DataDesignacao></Relatoria><Relatoria><Materia><IdentificacaoMateria><CodigoMateria>134909</CodigoMateria><SiglaCasaIdentificacaoMateria>SF</SiglaCasaIdentificacaoMateria><NomeCasaIdentificacaoMateria>Senado Federal</NomeCasaIdentificacaoMateria><SiglaSubtipoMateria>PLC</SiglaSubtipoMateria><DescricaoSubtipoMateria>PROJETO DE LEI DA CÂMARA</DescricaoSubtipoMateria><NumeroMateria>00134</NumeroMateria><AnoMateria>2018</AnoMateria></IdentificacaoMateria><EmentaMateria>Altera o art. 32 da Lei nº 9.605, de 12 de fevereiro de 1998, para agravar a pena pela prática de ato de abuso, consistente em maus-tratos ou mutilação de animais silvestres, domésticos ou domesticados, nativos ou exóticos, e instituir como causa de aumento de pena do crime de maus-tratos aos animais a prática de atos de zoofilia.</EmentaMateria></Materia><IdentificacaoComissao><CodigoComissao>50</CodigoComissao><SiglaComissao>CMA</SiglaComissao><NomeComissao>Comissão de Meio Ambiente</NomeComissao><SiglaCasaComissao>SF</SiglaCasaComissao><NomeCasaComissao>Senado Federal</NomeCasaComissao></IdentificacaoComissao><DescricaoTipoRelator>Relator</DescricaoTipoRelator><DataDesignacao>2020-08-03</DataDesignacao></Relatoria><Relatoria><Materia><IdentificacaoMateria><CodigoMateria>134922</CodigoMateria><SiglaCasaIdentificacaoMateria>SF</SiglaCasaIdentificacaoMateria><NomeCasaIdentificacaoMateria>Senado Federal</NomeCasaIdentificacaoMateria><SiglaSubtipoMateria>PLS</SiglaSubtipoMateria><DescricaoSubtipoMateria>PROJETO DE LEI DO SENADO</DescricaoSubtipoMateria><NumeroMateria>00529</NumeroMateria><AnoMateria>2018</AnoMateria></IdentificacaoMateria><EmentaMateria>Altera as Leis nº 6.938, de 31 de agosto de 1981 – Política Nacional do Meio Ambiente; nº 10.257, de 10 de julho de 2001 – Estatuto da Cidade; nº 12.651, de 25 de maio de 2012 – Código Florestal; e nº 6.766, de 19 de dezembro de 1979 – Lei de Parcelamento do Solo Urbano, para fortalecer a autonomia local e a segurança jurídica em matéria ambiental e urbanística.</EmentaMateria></Materia><IdentificacaoComissao><CodigoComissao>1306</CodigoComissao><SiglaComissao>CDR</SiglaComissao><NomeComissao>Comissão de Desenvolvimento Regional e Turismo</NomeComissao><SiglaCasaComissao>SF</SiglaCasaComissao><NomeCasaComissao>Senado Federal</NomeCasaComissao></IdentificacaoComissao><DescricaoTipoRelator>Relator</DescricaoTipoRelator><DataDesignacao>2019-03-21</DataDesignacao></Relatoria><Relatoria><Materia><IdentificacaoMateria><CodigoMateria>135450</CodigoMateria><SiglaCasaIdentificacaoMateria>SF</SiglaCasaIdentificacaoMateria><NomeCasaIdentificacaoMateria>Senado Federal</NomeCasaIdentificacaoMateria><SiglaSubtipoMateria>PL</SiglaSubtipoMateria><DescricaoSubtipoMateria>PROJETO DE LEI</DescricaoSubtipoMateria><NumeroMateria>01120</NumeroMateria><AnoMateria>2019</AnoMateria></IdentificacaoMateria><EmentaMateria>Altera o art. 101 da Lei nº 8.069, de 13 de julho de 1990 (Estatuto da Criança e do Adolescente - ECA), para incluir a Defensoria Pública como legitimada a ter acesso ao cadastro da criança ou adolescente submetido a medida de proteção.</EmentaMateria></Materia><IdentificacaoComissao><CodigoComissao>834</CodigoComissao><SiglaComissao>CDH</SiglaComissao><NomeComissao>Comissão de Direitos Humanos e Legislação Participativa</NomeComissao><SiglaCasaComissao>SF</SiglaCasaComissao><NomeCasaComissao>Senado Federal</NomeCasaComissao></IdentificacaoComissao><DescricaoTipoRelator>Relator</DescricaoTipoRelator><DataDesignacao>2019-03-22</DataDesignacao></Relatoria><Relatoria><Materia><IdentificacaoMateria><CodigoMateria>135499</CodigoMateria><SiglaCasaIdentificacaoMateria>SF</SiglaCasaIdentificacaoMateria><NomeCasaIdentificacaoMateria>Senado Federal</NomeCasaIdentificacaoMateria><SiglaSubtipoMateria>PL</SiglaSubtipoMateria><DescricaoSubtipoMateria>PROJETO DE LEI</DescricaoSubtipoMateria><NumeroMateria>01232</NumeroMateria><AnoMateria>2019</AnoMateria></IdentificacaoMateria><EmentaMateria>Altera o inciso XVIII do art. 20 da Lei nº 8.036, de 11 de maio de 1990, que “Dispõe sobre o Fundo de Garantia do Tempo de Serviço, e dá outras providências”, para incluir os dependentes do trabalhador na hipótese de saque do FGTS para aquisição de órteses e próteses, em razão de deficiência.</EmentaMateria></Materia><IdentificacaoComissao><CodigoComissao>40</CodigoComissao><SiglaComissao>CAS</SiglaComissao><NomeComissao>Comissão de Assuntos Sociais</NomeComissao><SiglaCasaComissao>SF</SiglaCasaComissao><NomeCasaComissao>Senado Federal</NomeCasaComissao></IdentificacaoComissao><DescricaoTipoRelator>Relator</DescricaoTipoRelator><DataDesignacao>2019-05-08</DataDesignacao></Relatoria><Relatoria><Materia><IdentificacaoMateria><CodigoMateria>136581</CodigoMateria><SiglaCasaIdentificacaoMateria>SF</SiglaCasaIdentificacaoMateria><NomeCasaIdentificacaoMateria>Senado Federal</NomeCasaIdentificacaoMateria><SiglaSubtipoMateria>PL</SiglaSubtipoMateria><DescricaoSubtipoMateria>PROJETO DE LEI</DescricaoSubtipoMateria><NumeroMateria>02633</NumeroMateria><AnoMateria>2019</AnoMateria></IdentificacaoMateria><EmentaMateria>Altera a Lei nº 13.301, de 27 de junho de 2016, e a Lei nº 13.146, de 6 de julho de 2015, para ampliar os direitos de mães, pais e crianças vítimas de microcefalia e sequelas neurológicas decorrentes de doenças transmitidas pelo Aedes aegypti.</EmentaMateria></Materia><IdentificacaoComissao><CodigoComissao>834</CodigoComissao><SiglaComissao>CDH</SiglaComissao><NomeComissao>Comissão de Direitos Humanos e Legislação Participativa</NomeComissao><SiglaCasaComissao>SF</SiglaCasaComissao><NomeCasaComissao>Senado Federal</NomeCasaComissao></IdentificacaoComissao><DescricaoTipoRelator>Relator</DescricaoTipoRelator><DataDesignacao>2019-05-20</DataDesignacao></Relatoria><Relatoria><Materia><IdentificacaoMateria><CodigoMateria>136663</CodigoMateria><SiglaCasaIdentificacaoMateria>SF</SiglaCasaIdentificacaoMateria><NomeCasaIdentificacaoMateria>Senado Federal</NomeCasaIdentificacaoMateria><SiglaSubtipoMateria>PL</SiglaSubtipoMateria><DescricaoSubtipoMateria>PROJETO DE LEI</DescricaoSubtipoMateria><NumeroMateria>02752</NumeroMateria><AnoMateria>2019</AnoMateria></IdentificacaoMateria><EmentaMateria>Denomina o Túnel que faz a divisa dos municípios de Mairiporã e São Paulo, na Rodovia Fernão Dias (BR 381), de Túnel da Mata Fria Salatiel Pereira do Valle.</EmentaMateria></Materia><IdentificacaoComissao><CodigoComissao>47</CodigoComissao><SiglaComissao>CE</SiglaComissao><NomeComissao>Comissão de Educação, Cultura e Esporte</NomeComissao><SiglaCasaComissao>SF</SiglaCasaComissao><NomeCasaComissao>Senado Federal</NomeCasaComissao></IdentificacaoComissao><DescricaoTipoRelator>Relator</DescricaoTipoRelator><DataDesignacao>2019-07-02</DataDesignacao></Relatoria><Relatoria><Materia><IdentificacaoMateria><CodigoMateria>137870</CodigoMateria><SiglaCasaIdentificacaoMateria>SF</SiglaCasaIdentificacaoMateria><NomeCasaIdentificacaoMateria>Senado Federal</NomeCasaIdentificacaoMateria><SiglaSubtipoMateria>PL</SiglaSubtipoMateria><DescricaoSubtipoMateria>PROJETO DE LEI</DescricaoSubtipoMateria><NumeroMateria>04216</NumeroMateria><AnoMateria>2019</AnoMateria></IdentificacaoMateria><EmentaMateria>Cria o Fundo de Apoio ao Sistema Nacional de Atendimento Socioeducativo.</EmentaMateria></Materia><IdentificacaoComissao><CodigoComissao>834</CodigoComissao><SiglaComissao>CDH</SiglaComissao><NomeComissao>Comissão de Direitos Humanos e Legislação Participativa</NomeComissao><SiglaCasaComissao>SF</SiglaCasaComissao><NomeCasaComissao>Senado Federal</NomeCasaComissao></IdentificacaoComissao><DescricaoTipoRelator>Relator</DescricaoTipoRelator><DataDesignacao>2019-09-18</DataDesignacao></Relatoria><Relatoria><Materia><IdentificacaoMateria><CodigoMateria>138331</CodigoMateria><SiglaCasaIdentificacaoMateria>SF</SiglaCasaIdentificacaoMateria><NomeCasaIdentificacaoMateria>Senado Federal</NomeCasaIdentificacaoMateria><SiglaSubtipoMateria>PL</SiglaSubtipoMateria><DescricaoSubtipoMateria>PROJETO DE LEI</DescricaoSubtipoMateria><NumeroMateria>04696</NumeroMateria><AnoMateria>2019</AnoMateria></IdentificacaoMateria><EmentaMateria>Altera o artigo 627 da Consolidação das Leis do Trabalho (CLT), aprovada pelo Decreto-Lei nº 5.452, de 1º de maio de 1943, para dispor sobre a observância do critério de dupla visita na fiscalização do trabalho.</EmentaMateria></Materia><IdentificacaoComissao><CodigoComissao>40</CodigoComissao><SiglaComissao>CAS</SiglaComissao><NomeComissao>Comissão de Assuntos Sociais</NomeComissao><SiglaCasaComissao>SF</SiglaCasaComissao><NomeCasaComissao>Senado Federal</NomeCasaComissao></IdentificacaoComissao><DescricaoTipoRelator>Relator</DescricaoTipoRelator><DataDesignacao>2019-12-03</DataDesignacao></Relatoria><Relatoria><Materia><IdentificacaoMateria><CodigoMateria>138694</CodigoMateria><SiglaCasaIdentificacaoMateria>SF</SiglaCasaIdentificacaoMateria><NomeCasaIdentificacaoMateria>Senado Federal</NomeCasaIdentificacaoMateria><SiglaSubtipoMateria>PL</SiglaSubtipoMateria><DescricaoSubtipoMateria>PROJETO DE LEI</DescricaoSubtipoMateria><NumeroMateria>04978</NumeroMateria><AnoMateria>2019</AnoMateria></IdentificacaoMateria><EmentaMateria>Altera a Lei nº 9.605, de 12 de fevereiro de 1998, para dispor sobre a destinação de animais domésticos e exóticos apreendidos e para proibir seu sacrifício.</EmentaMateria></Materia><IdentificacaoComissao><CodigoComissao>50</CodigoComissao><SiglaComissao>CMA</SiglaComissao><NomeComissao>Comissão de Meio Ambiente</NomeComissao><SiglaCasaComissao>SF</SiglaCasaComissao><NomeCasaComissao>Senado Federal</NomeCasaComissao></IdentificacaoComissao><DescricaoTipoRelator>Relator</DescricaoTipoRelator><DataDesignacao>2019-09-12</DataDesignacao></Relatoria><Relatoria><Materia><IdentificacaoMateria><CodigoMateria>138936</CodigoMateria><SiglaCasaIdentificacaoMateria>SF</SiglaCasaIdentificacaoMateria><NomeCasaIdentificacaoMateria>Senado Federal</NomeCasaIdentificacaoMateria><SiglaSubtipoMateria>PL</SiglaSubtipoMateria><DescricaoSubtipoMateria>PROJETO DE LEI</DescricaoSubtipoMateria><NumeroMateria>05185</NumeroMateria><AnoMateria>2019</AnoMateria></IdentificacaoMateria><EmentaMateria>Altera a Lei nº 9.394, de 20 de dezembro de 1996, que estabelece as diretrizes e bases da educação nacional, para prever, na educação superior, o atendimento às necessidades educativas das pessoas com transtornos específicos da aprendizagem e do desenvolvimento.</EmentaMateria></Materia><IdentificacaoComissao><CodigoComissao>834</CodigoComissao><SiglaComissao>CDH</SiglaComissao><NomeComissao>Comissão de Direitos Humanos e Legislação Participativa</NomeComissao><SiglaCasaComissao>SF</SiglaCasaComissao><NomeCasaComissao>Senado Federal</NomeCasaComissao></IdentificacaoComissao><DescricaoTipoRelator>Relator</DescricaoTipoRelator><DataDesignacao>2019-10-03</DataDesignacao></Relatoria><Relatoria><Materia><IdentificacaoMateria><CodigoMateria>139484</CodigoMateria><SiglaCasaIdentificacaoMateria>SF</SiglaCasaIdentificacaoMateria><NomeCasaIdentificacaoMateria>Senado Federal</NomeCasaIdentificacaoMateria><SiglaSubtipoMateria>PL</SiglaSubtipoMateria><DescricaoSubtipoMateria>PROJETO DE LEI</DescricaoSubtipoMateria><NumeroMateria>05609</NumeroMateria><AnoMateria>2019</AnoMateria></IdentificacaoMateria><EmentaMateria>Altera a Lei nº 11.340, de 7 de agosto de 2006, que cria mecanismos para coibir a violência doméstica e familiar contra a mulher, para aperfeiçoar a proteção da mulher.</EmentaMateria></Materia><IdentificacaoComissao><CodigoComissao>834</CodigoComissao><SiglaComissao>CDH</SiglaComissao><NomeComissao>Comissão de Direitos Humanos e Legislação Participativa</NomeComissao><SiglaCasaComissao>SF</SiglaCasaComissao><NomeCasaComissao>Senado Federal</NomeCasaComissao></IdentificacaoComissao><DescricaoTipoRelator>Relator</DescricaoTipoRelator><DataDesignacao>2019-11-20</DataDesignacao></Relatoria><Relatoria><Materia><IdentificacaoMateria><CodigoMateria>139511</CodigoMateria><SiglaCasaIdentificacaoMateria>SF</SiglaCasaIdentificacaoMateria><NomeCasaIdentificacaoMateria>Senado Federal</NomeCasaIdentificacaoMateria><SiglaSubtipoMateria>PEC</SiglaSubtipoMateria><DescricaoSubtipoMateria>PROPOSTA DE EMENDA À CONSTITUIÇÃO</DescricaoSubtipoMateria><NumeroMateria>00177</NumeroMateria><AnoMateria>2019</AnoMateria></IdentificacaoMateria><EmentaMateria>Altera o art. 37 da Constituição Federal, para vedar a exoneração ad nutum da servidora ocupante de cargo em comissão desde a confirmação da gravidez até cinco meses após o parto.</EmentaMateria></Materia><IdentificacaoComissao><CodigoComissao>34</CodigoComissao><SiglaComissao>CCJ</SiglaComissao><NomeComissao>Comissão de Constituição, Justiça e Cidadania</NomeComissao><SiglaCasaComissao>SF</SiglaCasaComissao><NomeCasaComissao>Senado Federal</NomeCasaComissao></IdentificacaoComissao><DescricaoTipoRelator>Relator</DescricaoTipoRelator><DataDesignacao>2020-02-20</DataDesignacao></Relatoria><Relatoria><Materia><IdentificacaoMateria><CodigoMateria>139858</CodigoMateria><SiglaCasaIdentificacaoMateria>SF</SiglaCasaIdentificacaoMateria><NomeCasaIdentificacaoMateria>Senado Federal</NomeCasaIdentificacaoMateria><SiglaSubtipoMateria>PL</SiglaSubtipoMateria><DescricaoSubtipoMateria>PROJETO DE LEI</DescricaoSubtipoMateria><NumeroMateria>06033</NumeroMateria><AnoMateria>2019</AnoMateria></IdentificacaoMateria><EmentaMateria>Institui incentivos fiscais para operações com produtos sem lactose e produtos orgânicos.</EmentaMateria></Materia><IdentificacaoComissao><CodigoComissao>1307</CodigoComissao><SiglaComissao>CRA</SiglaComissao><NomeComissao>Comissão de Agricultura e Reforma Agrária</NomeComissao><SiglaCasaComissao>SF</SiglaCasaComissao><NomeCasaComissao>Senado Federal</NomeCasaComissao></IdentificacaoComissao><DescricaoTipoRelator>Relator</DescricaoTipoRelator><DataDesignacao>2020-03-11</DataDesignacao></Relatoria><Relatoria><Materia><IdentificacaoMateria><CodigoMateria>140299</CodigoMateria><SiglaCasaIdentificacaoMateria>SF</SiglaCasaIdentificacaoMateria><NomeCasaIdentificacaoMateria>Senado Federal</NomeCasaIdentificacaoMateria><SiglaSubtipoMateria>PL</SiglaSubtipoMateria><DescricaoSubtipoMateria>PROJETO DE LEI</DescricaoSubtipoMateria><NumeroMateria>03191</NumeroMateria><AnoMateria>2019</AnoMateria><DescricaoObjetivoProcesso>Substitutivo-CD</DescricaoObjetivoProcesso></IdentificacaoMateria><EmentaMateria>Altera a Lei nº 9.099, de 26 de setembro de 1995, para prever ressalvas à gratuidade das despesas no âmbito dos Juizados Especiais.</EmentaMateria></Materia><IdentificacaoComissao><CodigoComissao>34</CodigoComissao><SiglaComissao>CCJ</SiglaComissao><NomeComissao>Comissão de Constituição, Justiça e Cidadania</NomeComissao><SiglaCasaComissao>SF</SiglaCasaComissao><NomeCasaComissao>Senado Federal</NomeCasaComissao></IdentificacaoComissao><DescricaoTipoRelator>Relator</DescricaoTipoRelator><DataDesignacao>2020-02-06</DataDesignacao></Relatoria><Relatoria><Materia><IdentificacaoMateria><CodigoMateria>140302</CodigoMateria><SiglaCasaIdentificacaoMateria>SF</SiglaCasaIdentificacaoMateria><NomeCasaIdentificacaoMateria>Senado Federal</NomeCasaIdentificacaoMateria><SiglaSubtipoMateria>PL</SiglaSubtipoMateria><DescricaoSubtipoMateria>PROJETO DE LEI</DescricaoSubtipoMateria><NumeroMateria>06560</NumeroMateria><AnoMateria>2019</AnoMateria></IdentificacaoMateria><EmentaMateria>Institui a Política Nacional de Incentivo à Produção Melífera e ao Desenvolvimento de Produtos e Serviços Apícolas e Meliponícolas de Qualidade.</EmentaMateria></Materia><IdentificacaoComissao><CodigoComissao>1307</CodigoComissao><SiglaComissao>CRA</SiglaComissao><NomeComissao>Comissão de Agricultura e Reforma Agrária</NomeComissao><SiglaCasaComissao>SF</SiglaCasaComissao><NomeCasaComissao>Senado Federal</NomeCasaComissao></IdentificacaoComissao><DescricaoTipoRelator>Relator</DescricaoTipoRelator><DataDesignacao>2020-03-11</DataDesignacao></Relatoria></RelatoriasAtuais><OutrasInformacoes><Servico><NomeServico>ApartesParlamentar</NomeServico><DescricaoServico>Apartes do parlamentar</DescricaoServico><UrlServico>http://legis.senado.leg.br/dadosabertos/senador/5988/apartes?v=4</UrlServico></Servico><Servico><NomeServico>CargoParlamentar</NomeServico><DescricaoServico>Cargos do parlamentar ao longo do(s) mandato(s)</DescricaoServico><UrlServico>http://legis.senado.leg.br/dadosabertos/senador/5988/cargos?v=4</UrlServico></Servico><Servico><NomeServico>DiscursosParlamentar</NomeServico><DescricaoServico>Discursos do parlamentar. Atualizações na versão: 05/12/2019 - o tipo de pronunciamento deixou de existir, ele foi substituído pelo Tipo de uso da palavra - tag TipoUsoPalavra.</DescricaoServico><UrlServico>http://legis.senado.leg.br/dadosabertos/senador/5988/discursos?v=4</UrlServico></Servico><Servico><NomeServico>FiliacaoParlamentar</NomeServico><DescricaoServico>Filiações partidárias do parlamentar ao longo do(s) mandato(s)</DescricaoServico><UrlServico>http://legis.senado.leg.br/dadosabertos/senador/5988/filiacoes?v=4</UrlServico></Servico><Servico><NomeServico>LicencaParlamentar</NomeServico><DescricaoServico>Licenças do parlamentar.</DescricaoServico><UrlServico>http://legis.senado.leg.br/dadosabertos/senador/5988/licencas?v=4</UrlServico></Servico><Servico><NomeServico>LiderancaParlamentar</NomeServico><DescricaoServico>Cargos de liderança do parlamentar ao longo do(s) mandato(s)</DescricaoServico><UrlServico>http://legis.senado.leg.br/dadosabertos/senador/5988/liderancas?v=4</UrlServico></Servico><Servico><NomeServico>MandatoParlamentar</NomeServico><DescricaoServico>Mandatos do parlamentar (atual e anteriores, se houver)</DescricaoServico><UrlServico>http://legis.senado.leg.br/dadosabertos/senador/5988/mandatos?v=4</UrlServico></Servico><Servico><NomeServico>MateriasAutoriaParlamentar</NomeServico><DescricaoServico>Matérias de autoria ou coautoria do parlamentar
      
      ATENÇÃO: a tag &quot;Descontinuacao&quot;, dentro de &quot;Metadados&quot; traz informações sobre a descontinuação deste serviço, indicando o serviço e/ou versão substitut</DescricaoServico><UrlServico>http://legis.senado.leg.br/dadosabertos/senador/5988/autorias?v=4</UrlServico></Servico><Servico><NomeServico>MateriasRelatoriaParlamentar</NomeServico><DescricaoServico>Matérias relatadas pelo parlamentar
      
      ATENÇÃO: a tag &quot;Descontinuacao&quot;, dentro de &quot;Metadados&quot; traz informações sobre a descontinuação deste serviço, indicando o serviço e/ou versão substitutos.</DescricaoServico><UrlServico>http://legis.senado.leg.br/dadosabertos/senador/5988/relatorias?v=4</UrlServico></Servico><Servico><NomeServico>MembroComissaoParlamentar</NomeServico><DescricaoServico>Comissões em que o parlamentar é (ou foi) membro</DescricaoServico><UrlServico>http://legis.senado.leg.br/dadosabertos/senador/5988/comissoes?v=4</UrlServico></Servico><Servico><NomeServico>VotacaoParlamentar</NomeServico><DescricaoServico>Votos do parlamentar ao longo do(s) mandato(s)</DescricaoServico><UrlServico>http://legis.senado.leg.br/dadosabertos/senador/5988/votacoes?v=4</UrlServico></Servico></OutrasInformacoes><UrlGlossario>http://legis.senado.leg.br/dadosabertos/senador/</UrlGlossario>
   </Parlamentar>
</DetalheParlamentar>
